systems_manager/__init__.py
systems_manager/__main__.py
systems_manager/mcp_config.json
systems_manager/middlewares.py
systems_manager/systems_manager.py
systems_manager/systems_manager_agent.py
systems_manager/systems_manager_mcp.py
systems_manager/utils.py
systems_manager/skills/bash/SKILL.md
systems_manager/skills/systems-manager-linux/SKILL.md
systems_manager/skills/systems-manager-system-management/SKILL.md
systems_manager/skills/systems-manager-windows/SKILL.md
systems_manager/skills/text_editor/SKILL.md
systems_manager-1.1.26.dist-info/licenses/LICENSE
systems_manager-1.1.26.dist-info/METADATA
systems_manager-1.1.26.dist-info/WHEEL
systems_manager-1.1.26.dist-info/entry_points.txt
systems_manager-1.1.26.dist-info/top_level.txt
systems_manager-1.1.26.dist-info/RECORD
